data_potty-0.0.0.dist-info/DESCRIPTION.rst
data_potty-0.0.0.dist-info/METADATA
data_potty-0.0.0.dist-info/RECORD
data_potty-0.0.0.dist-info/WHEEL
data_potty-0.0.0.dist-info/metadata.json
data_potty-0.0.0.dist-info/top_level.txt
potty/__init__.py
