Metadata-Version: 2.0
Name: data-potty
Version: 0.0.0
Summary: Client for dxpot
Home-page: https://github.com/claydodo/potty
Author: claydodo and his little friends (xiao huo ban)
Author-email: claydodo@foxmail.com
License: UNKNOWN
Platform: UNKNOWN
Classifier: Programming Language :: Python :: 3 
Classifier: Operating System :: OS Independent
